tweezers/__init__.py
tweezers/api.py
tweezers/auth.py
tweezers/search.py
tweezers-0.0.2.dist-info/LICENSE
tweezers-0.0.2.dist-info/METADATA
tweezers-0.0.2.dist-info/WHEEL
tweezers-0.0.2.dist-info/top_level.txt
tweezers-0.0.2.dist-info/RECORD
