Metadata-Version: 2.1
Name: tweezers
Version: 0.0.2
Summary: A lightweight library for scraping Twitter data.
Home-page: https://github.com/toby-p/tweezers
Author: Toby Petty
Author-email: toby.b.petty@gmail.com
License: MIT
Keywords: api,twitter,data
Platform: UNKNOWN
Classifier: Development Status :: 4 - Beta
Classifier: Intended Audience :: End Users/Desktop
Classifier: License :: OSI Approved :: MIT License
Classifier: Programming Language :: Python :: 3.6
Requires-Python: >=3.9
Requires-Dist: pandas (>=1.2.4)
Requires-Dist: requests (>=2.25.1)
Requires-Dist: requests-oauthlib (>=1.3.0)
Requires-Dist: textblob (>=0.15.3)
